tmp/job_1/FullStep.v
// Generator : SpinalHDL v1.8.0    git head : 4e3563a282582b41f4eaafc503787757251d23ea
// Component : FullStep

`timescale 1ns/1ps

module FullStep (
  output     [15:0]   c_data,
  output     [15:0]   d1_data,
  output     [15:0]   d2_data,
  input               clk,
  input               reset
);

  reg        [15:0]   _zz_c_rom_port0;
  reg        [15:0]   _zz_d1_rom_port0;
  reg        [15:0]   _zz_d1_rom_port1;
  wire                _zz_c_rom_port;
  wire                _zz_c_data;
  wire                _zz_d1_rom_port;
  wire                _zz_d1_data;
  wire                _zz_d1_rom_port_1;
  wire       [16:0]   _zz_d2_data;
  wire       [16:0]   _zz_d2_data_1;
  wire       [15:0]   _zz_d2_data_2;
  wire                _zz_d2_data_3;
  wire       [0:0]    _zz_d2_data_4;
  wire       [15:0]   Sample;
  reg        [8:0]    i;
  wire                when_FullStep_l70;
  reg [15:0] c_rom [0:351];
  reg [15:0] d1_rom [0:351];

  assign _zz_d2_data = _zz_d2_data_1;
  assign _zz_d2_data_1 = ($signed(_zz_d2_data_2) * $signed(_zz_d2_data_4));
  assign _zz_d2_data_2 = _zz_d1_rom_port1;
  assign _zz_d2_data_4 = 1'b1;
  assign _zz_c_data = 1'b1;
  assign _zz_d1_data = 1'b1;
  assign _zz_d2_data_3 = 1'b1;
  initial begin
    $readmemb("D:\\SCALA\\Xil_Master\\tmp\\job_1\\FullStep.v_toplevel_c_rom.bin",c_rom);
  end
  always @(posedge clk) begin
    if(_zz_c_data) begin
      _zz_c_rom_port0 <= c_rom[i];
    end
  end

  initial begin
    $readmemb("D:\\SCALA\\Xil_Master\\tmp\\job_1\\FullStep.v_toplevel_d1_rom.bin",d1_rom);
  end
  always @(posedge clk) begin
    if(_zz_d1_data) begin
      _zz_d1_rom_port0 <= d1_rom[i];
    end
  end

  always @(posedge clk) begin
    if(_zz_d2_data_3) begin
      _zz_d1_rom_port1 <= d1_rom[i];
    end
  end

  assign when_FullStep_l70 = (i < 9'h15f); // @[BaseType.scala 305:24]
  assign c_data = _zz_c_rom_port0; // @[FullStep.scala 75:13]
  assign d1_data = _zz_d1_rom_port0; // @[FullStep.scala 76:14]
  assign d2_data = _zz_d2_data[15:0]; // @[FullStep.scala 77:14]
  always @(posedge clk or posedge reset) begin
    if(reset) begin
      i <= 9'h0; // @[Data.scala 400:33]
    end else begin
      if(when_FullStep_l70) begin
        i <= (i + 9'h001); // @[FullStep.scala 71:7]
      end else begin
        i <= 9'h0; // @[FullStep.scala 73:7]
      end
    end
  end


endmodule

simWorkspace/FullStep/test.vcd
$version Generated by VerilatedVcd $end
$date 05/23/23 11:18:45 $end
$timescale 1ps $end

 $scope module TOP $end
  $var wire 16 # c_data [15:0] $end
  $var wire  1 & clk $end
  $var wire 16 $ d1_data [15:0] $end
  $var wire 16 % d2_data [15:0] $end
  $var wire  1 ' reset $end
  $scope module FullStep $end
   $var wire 16 * Sample [15:0] $end
   $var wire 16 # c_data [15:0] $end
   $var wire  1 & clk $end
   $var wire 16 $ d1_data [15:0] $end
   $var wire 16 % d2_data [15:0] $end
   $var wire  9 ( i [8:0] $end
   $var wire  1 ' reset $end
   $var wire  1 ) when_FullStep_l70 $end
  $upscope $end
 $upscope $end
$enddefinitions $end


#0
b1001001101100110 #
b0101110100011001 $
b1110111001000001 %
0&
1'
b000000000 (
1)
b0011101000011111 *
#160
0'
#170
b0000000000000000 #
b1000000000000001 $
b0111111111111111 %
1&
b000000001 (
#175
0&
#180
b0000010111010001 #
1&
b000000010 (
#185
0&
#190
b0000101110100010 #
1&
b000000011 (
#195
0&
#200
b0001000101110100 #
1&
b000000100 (
#205
0&
#210
b0001011101000101 #
1&
b000000101 (
#215
0&
#220
b0001110100010111 #
1&
b000000110 (
#225
0&
#230
b0010001011101000 #
1&
b000000111 (
#235
0&
#240
b0010100010111001 #
1&
b000001000 (
#245
0&
#250
b0010111010001011 #
1&
b000001001 (
#255
0&
#260
b0011010001011100 #
1&
b000001010 (
#265
0&
#270
b0011101000101110 #
1&
b000001011 (
#275
0&
#280
b0011111111111111 #
1&
b000001100 (
#285
0&
#290
b0100010111010000 #
1&
b000001101 (
#295
0&
#300
b0100101110100010 #
1&
b000001110 (
#305
0&
#310
b0101000101110011 #
1&
b000001111 (
#315
0&
#320
b0101011101000101 #
1&
b000010000 (
#325
0&
#330
b0101110100010110 #
1&
b000010001 (
#335
0&
#340
b0110001011100111 #
1&
b000010010 (
#345
0&
#350
b0110100010111001 #
1&
b000010011 (
#355
0&
#360
b0110111010001010 #
1&
b000010100 (
#365
0&
#370
b0111010001011100 #
1&
b000010101 (
#375
0&
#380
b0111101000101101 #
1&
b000010110 (
#385
0&
#390
b0111111111111111 #
b1000000000001100 $
b0111111111110100 %
1&
b000010111 (
#395
0&
#400
b1000000111111101 $
b0111111000000011 %
1&
b000011000 (
#405
0&
#410
b1000001111101101 $
b0111110000010011 %
1&
b000011001 (
#415
0&
#420
b1000010111011110 $
b0111101000100010 %
1&
b000011010 (
#425
0&
#430
b1000011111001110 $
b0111100000110010 %
1&
b000011011 (
#435
0&
#440
b1000100110111111 $
b0111011001000001 %
1&
b000011100 (
#445
0&
#450
b1000101110101111 $
b0111010001010001 %
1&
b000011101 (
#455
0&
#460
b1000110110100000 $
b0111001001100000 %
1&
b000011110 (
#465
0&
#470
b1000111110010000 $
b0111000001110000 %
1&
b000011111 (
#475
0&
#480
b1001000110000001 $
b0110111001111111 %
1&
b000100000 (
#485
0&
#490
b1001001101110001 $
b0110110010001111 %
1&
b000100001 (
#495
0&
#500
b1001010101100010 $
b0110101010011110 %
1&
b000100010 (
#505
0&
#510
b1001011101010010 $
b0110100010101110 %
1&
b000100011 (
#515
0&
#520
b1001100101000011 $
b0110011010111101 %
1&
b000100100 (
#525
0&
#530
b1001101100110011 $
b0110010011001101 %
1&
b000100101 (
#535
0&
#540
b1001110100100011 $
b0110001011011101 %
1&
b000100110 (
#545
0&
#550
b1001111100010100 $
b0110000011101100 %
1&
b000100111 (
#555
0&
#560
b1010000100000100 $
b0101111011111100 %
1&
b000101000 (
#565
0&
#570
b1010001011110101 $
b0101110100001011 %
1&
b000101001 (
#575
0&
#580
b1010010011100101 $
b0101101100011011 %
1&
b000101010 (
#585
0&
#590
b1010011011010110 $
b0101100100101010 %
1&
b000101011 (
#595
0&
#600
b1010100011000110 $
b0101011100111010 %
1&
b000101100 (
#605
0&
#610
b1010101010110111 $
b0101010101001001 %
1&
b000101101 (
#615
0&
#620
b1010110010100111 $
b0101001101011001 %
1&
b000101110 (
#625
0&
#630
b1010111010011000 $
b0101000101101000 %
1&
b000101111 (
#635
0&
#640
b1011000010001000 $
b0100111101111000 %
1&
b000110000 (
#645
0&
#650
b1011001001111001 $
b0100110110000111 %
1&
b000110001 (
#655
0&
#660
b1011010001101001 $
b0100101110010111 %
1&
b000110010 (
#665
0&
#670
b1011011001011010 $
b0100100110100110 %
1&
b000110011 (
#675
0&
#680
b1011100001001010 $
b0100011110110110 %
1&
b000110100 (
#685
0&
#690
b1011101000111011 $
b0100010111000101 %
1&
b000110101 (
#695
0&
#700
b1011110000101011 $
b0100001111010101 %
1&
b000110110 (
#705
0&
#710
b1011111000011011 $
b0100000111100101 %
1&
b000110111 (
#715
0&
#720
b1100000000001100 $
b0011111111110100 %
1&
b000111000 (
#725
0&
#730
b1100000111111100 $
b0011111000000100 %
1&
b000111001 (
#735
0&
#740
b1100001111101101 $
b0011110000010011 %
1&
b000111010 (
#745
0&
#750
b1100010111011101 $
b0011101000100011 %
1&
b000111011 (
#755
0&
#760
b1100011111001110 $
b0011100000110010 %
1&
b000111100 (
#765
0&
#770
b1100100110111110 $
b0011011001000010 %
1&
b000111101 (
#775
0&
#780
b1100101110101111 $
b0011010001010001 %
1&
b000111110 (
#785
0&
#790
b1100110110011111 $
b0011001001100001 %
1&
b000111111 (
#795
0&
#800
b1100111110010000 $
b0011000001110000 %
1&
b001000000 (
#805
0&
#810
b1101000110000000 $
b0010111010000000 %
1&
b001000001 (
#815
0&
#820
b1101001101110001 $
b0010110010001111 %
1&
b001000010 (
#825
0&
#830
b1101010101100001 $
b0010101010011111 %
1&
b001000011 (
#835
0&
#840
b1101011101010010 $
b0010100010101110 %
1&
b001000100 (
#845
0&
#850
b1101100101000010 $
b0010011010111110 %
1&
b001000101 (
#855
0&
#860
b1101101100110010 $
b0010010011001110 %
1&
b001000110 (
#865
0&
#870
b1101110100100011 $
b0010001011011101 %
1&
b001000111 (
#875
0&
#880
b1101111100010011 $
b0010000011101101 %
1&
b001001000 (
#885
0&
#890
b1110000100000100 $
b0001111011111100 %
1&
b001001001 (
#895
0&
#900
b1110001011110100 $
b0001110100001100 %
1&
b001001010 (
#905
0&
#910
b1110010011100101 $
b0001101100011011 %
1&
b001001011 (
#915
0&
#920
b1110011011010101 $
b0001100100101011 %
1&
b001001100 (
#925
0&
#930
b1110100011000110 $
b0001011100111010 %
1&
b001001101 (
#935
0&
#940
b1110101010110110 $
b0001010101001010 %
1&
b001001110 (
#945
0&
#950
b1110110010100111 $
b0001001101011001 %
1&
b001001111 (
#955
0&
#960
b1110111010010111 $
b0001000101101001 %
1&
b001010000 (
#965
0&
#970
b1111000010001000 $
b0000111101111000 %
1&
b001010001 (
#975
0&
#980
b1111001001111000 $
b0000110110001000 %
1&
b001010010 (
#985
0&
#990
b1111010001101001 $
b0000101110010111 %
1&
b001010011 (
#995
0&
#1000
b1111011001011001 $
b0000100110100111 %
1&
b001010100 (
#1005
0&
#1010
b1111100001001010 $
b0000011110110110 %
1&
b001010101 (
#1015
0&
#1020
b1111101000111010 $
b0000010111000110 %
1&
b001010110 (
#1025
0&
#1030
b1111110000101010 $
b0000001111010110 %
1&
b001010111 (
#1035
0&
#1040
b1111111000011011 $
b0000000111100101 %
1&
b001011000 (
#1045
0&
#1050
b0000000000001010 $
b1111111111110110 %
1&
b001011001 (
#1055
0&
#1060
b0000000111111011 $
b1111111000000101 %
1&
b001011010 (
#1065
0&
#1070
b0000001111101011 $
b1111110000010101 %
1&
b001011011 (
#1075
0&
#1080
b0000010111011100 $
b1111101000100100 %
1&
b001011100 (
#1085
0&
#1090
b0000011111001100 $
b1111100000110100 %
1&
b001011101 (
#1095
0&
#1100
b0000100110111101 $
b1111011001000011 %
1&
b001011110 (
#1105
0&
#1110
b0000101110101101 $
b1111010001010011 %
1&
b001011111 (
#1115
0&
#1120
b0000110110011110 $
b1111001001100010 %
1&
b001100000 (
#1125
0&
#1130
b0000111110001110 $
b1111000001110010 %
1&
b001100001 (
#1135
0&
#1140
b0001000101111111 $
b1110111010000001 %
1&
b001100010 (
#1145
0&
#1150
b0001001101101111 $
b1110110010010001 %
1&
b001100011 (
#1155
0&
#1160
b0001010101100000 $
b1110101010100000 %
1&
b001100100 (
#1165
0&
#1170
b0001011101010000 $
b1110100010110000 %
1&
b001100101 (
#1175
0&
#1180
b0001100101000001 $
b1110011010111111 %
1&
b001100110 (
#1185
0&
#1190
b0001101100110001 $
b1110010011001111 %
1&
b001100111 (
#1195
0&
#1200
b0001110100100001 $
b1110001011011111 %
1&
b001101000 (
#1205
0&
#1210
b0001111100010010 $
b1110000011101110 %
1&
b001101001 (
#1215
0&
#1220
b0010000100000010 $
b1101111011111110 %
1&
b001101010 (
#1225
0&
#1230
b0010001011110011 $
b1101110100001101 %
1&
b001101011 (
#1235
0&
#1240
b0010010011100011 $
b1101101100011101 %
1&
b001101100 (
#1245
0&
#1250
b0010011011010100 $
b1101100100101100 %
1&
b001101101 (
#1255
0&
#1260
b0010100011000100 $
b1101011100111100 %
1&
b001101110 (
#1265
0&
#1270
b0010101010110101 $
b1101010101001011 %
1&
b001101111 (
#1275
0&
#1280
b0010110010100101 $
b1101001101011011 %
1&
b001110000 (
#1285
0&
#1290
b0010111010010110 $
b1101000101101010 %
1&
b001110001 (
#1295
0&
#1300
b0011000010000110 $
b1100111101111010 %
1&
b001110010 (
#1305
0&
#1310
b0011001001110111 $
b1100110110001001 %
1&
b001110011 (
#1315
0&
#1320
b0011010001100111 $
b1100101110011001 %
1&
b001110100 (
#1325
0&
#1330
b0011011001011000 $
b1100100110101000 %
1&
b001110101 (
#1335
0&
#1340
b0011100001001000 $
b1100011110111000 %
1&
b001110110 (
#1345
0&
#1350
b0011101000111001 $
b1100010111000111 %
1&
b001110111 (
#1355
0&
#1360
b0011110000101001 $
b1100001111010111 %
1&
b001111000 (
#1365
0&
#1370
b0011111000011001 $
b1100000111100111 %
1&
b001111001 (
#1375
0&
#1380
b0100000000001010 $
b1011111111110110 %
1&
b001111010 (
#1385
0&
#1390
b0100000111111010 $
b1011111000000110 %
1&
b001111011 (
#1395
0&
#1400
b0100001111101011 $
b1011110000010101 %
1&
b001111100 (
#1405
0&
#1410
b0100010111011011 $
b1011101000100101 %
1&
b001111101 (
#1415
0&
#1420
b0100011111001100 $
b1011100000110100 %
1&
b001111110 (
#1425
0&
#1430
b0100100110111100 $
b1011011001000100 %
1&
b001111111 (
#1435
0&
#1440
b0100101110101101 $
b1011010001010011 %
1&
b010000000 (
#1445
0&
#1450
b0100110110011101 $
b1011001001100011 %
1&
b010000001 (
#1455
0&
#1460
b0100111110001110 $
b1011000001110010 %
1&
b010000010 (
#1465
0&
#1470
b0101000101111110 $
b1010111010000010 %
1&
b010000011 (
#1475
0&
#1480
b0101001101101111 $
b1010110010010001 %
1&
b010000100 (
#1485
0&
#1490
b0101010101011111 $
b1010101010100001 %
1&
b010000101 (
#1495
0&
#1500
b0101011101010000 $
b1010100010110000 %
1&
b010000110 (
#1505
0&
#1510
b0101100101000000 $
b1010011011000000 %
1&
b010000111 (
#1515
0&
#1520
b0101101100110000 $
b1010010011010000 %
1&
b010001000 (
#1525
0&
#1530
b0101110100100001 $
b1010001011011111 %
1&
b010001001 (
#1535
0&
#1540
b0101111100010001 $
b1010000011101111 %
1&
b010001010 (
#1545
0&
#1550
b0110000100000010 $
b1001111011111110 %
1&
b010001011 (
#1555
0&
#1560
b0110001011110010 $
b1001110100001110 %
1&
b010001100 (
#1565
0&
#1570
b0110010011100011 $
b1001101100011101 %
1&
b010001101 (
#1575
0&
#1580
b0110011011010011 $
b1001100100101101 %
1&
b010001110 (
#1585
0&
#1590
b0110100011000100 $
b1001011100111100 %
1&
b010001111 (
#1595
0&
#1600
b0110101010110100 $
b1001010101001100 %
1&
b010010000 (
#1605
0&
#1610
b0110110010100101 $
b1001001101011011 %
1&
b010010001 (
#1615
0&
#1620
b0110111010010101 $
b1001000101101011 %
1&
b010010010 (
#1625
0&
#1630
b0111000010000110 $
b1000111101111010 %
1&
b010010011 (
#1635
0&
#1640
b0111001001110110 $
b1000110110001010 %
1&
b010010100 (
#1645
0&
#1650
b0111010001100111 $
b1000101110011001 %
1&
b010010101 (
#1655
0&
#1660
b0111011001010111 $
b1000100110101001 %
1&
b010010110 (
#1665
0&
#1670
b0111100001001000 $
b1000011110111000 %
1&
b010010111 (
#1675
0&
#1680
b0111101000111000 $
b1000010111001000 %
1&
b010011000 (
#1685
0&
#1690
b0111110000101000 $
b1000001111011000 %
1&
b010011001 (
#1695
0&
#1700
b0111111000011001 $
b1000000111100111 %
1&
b010011010 (
#1705
0&
#1710
b0111111111111111 $
b1000000000000001 %
1&
b010011011 (
#1715
0&
#1720
b0111101000101101 #
1&
b010011100 (
#1725
0&
#1730
b0111010001011100 #
1&
b010011101 (
#1735
0&
#1740
b0110111010001010 #
1&
b010011110 (
#1745
0&
#1750
b0110100010111001 #
1&
b010011111 (
#1755
0&
#1760
b0110001011100111 #
1&
b010100000 (
#1765
0&
#1770
b0101110100010110 #
1&
b010100001 (
#1775
0&
#1780
b0101011101000101 #
1&
b010100010 (
#1785
0&
#1790
b0101000101110011 #
1&
b010100011 (
#1795
0&
#1800
b0100101110100010 #
1&
b010100100 (
#1805
0&
#1810
b0100010111010000 #
1&
b010100101 (
#1815
0&
#1820
b0011111111111111 #
1&
b010100110 (
#1825
0&
#1830
b0011101000101110 #
1&
b010100111 (
#1835
0&
#1840
b0011010001011100 #
1&
b010101000 (
#1845
0&
#1850
b0010111010001011 #
1&
b010101001 (
#1855
0&
#1860
b0010100010111001 #
1&
b010101010 (
#1865
0&
#1870
b0010001011101000 #
1&
b010101011 (
#1875
0&
#1880
b0001110100010111 #
1&
b010101100 (
#1885
0&
#1890
b0001011101000101 #
1&
b010101101 (
#1895
0&
#1900
b0001000101110100 #
1&
b010101110 (
#1905
0&
#1910
b0000101110100010 #
1&
b010101111 (
#1915
0&
#1920
b0000010111010001 #
1&
b010110000 (
#1925
0&
#1930
b0000000000000000 #
1&
b010110001 (
#1935
0&
#1940
b1111101000101111 #
1&
b010110010 (
#1945
0&
#1950
b1111010001011110 #
1&
b010110011 (
#1955
0&
#1960
b1110111010001100 #
1&
b010110100 (
#1965
0&
#1970
b1110100010111011 #
1&
b010110101 (
#1975
0&
#1980
b1110001011101001 #
1&
b010110110 (
#1985
0&
#1990
b1101110100011000 #
1&
b010110111 (
#1995
0&
#2000
b1101011101000111 #
1&
b010111000 (
#2005
0&
#2010
b1101000101110101 #
1&
b010111001 (
#2015
0&
#2020
b1100101110100100 #
1&
b010111010 (
#2025
0&
#2030
b1100010111010010 #
1&
b010111011 (
#2035
0&
#2040
b1100000000000001 #
1&
b010111100 (
#2045
0&
#2050
b1011101000110000 #
1&
b010111101 (
#2055
0&
#2060
b1011010001011110 #
1&
b010111110 (
#2065
0&
#2070
b1010111010001101 #
1&
b010111111 (
#2075
0&
#2080
b1010100010111011 #
1&
b011000000 (
#2085
0&
#2090
b1010001011101010 #
1&
b011000001 (
#2095
0&
#2100
b1001110100011001 #
1&
b011000010 (
#2105
0&
#2110
b1001011101000111 #
1&
b011000011 (
#2115
0&
#2120
b1001000101110110 #
1&
b011000100 (
#2125
0&
#2130
b1000101110100100 #
1&
b011000101 (
#2135
0&
#2140
b1000010111010011 #
1&
b011000110 (
#2145
0&
#2150
b1000000000000001 #
1&
b011000111 (
#2155
0&
#2160
b0111111000001110 $
b1000000111110010 %
1&
b011001000 (
#2165
0&
#2170
b0111110000011110 $
b1000001111100010 %
1&
b011001001 (
#2175
0&
#2180
b0111101000101101 $
b1000010111010011 %
1&
b011001010 (
#2185
0&
#2190
b0111100000111101 $
b1000011111000011 %
1&
b011001011 (
#2195
0&
#2200
b0111011001001100 $
b1000100110110100 %
1&
b011001100 (
#2205
0&
#2210
b0111010001011100 $
b1000101110100100 %
1&
b011001101 (
#2215
0&
#2220
b0111001001101011 $
b1000110110010101 %
1&
b011001110 (
#2225
0&
#2230
b0111000001111011 $
b1000111110000101 %
1&
b011001111 (
#2235
0&
#2240
b0110111010001010 $
b1001000101110110 %
1&
b011010000 (
#2245
0&
#2250
b0110110010011010 $
b1001001101100110 %
1&
b011010001 (
#2255
0&
#2260
b0110101010101001 $
b1001010101010111 %
1&
b011010010 (
#2265
0&
#2270
b0110100010111001 $
b1001011101000111 %
1&
b011010011 (
#2275
0&
#2280
b0110011011001000 $
b1001100100111000 %
1&
b011010100 (
#2285
0&
#2290
b0110010011011000 $
b1001101100101000 %
1&
b011010101 (
#2295
0&
#2300
b0110001011100111 $
b1001110100011001 %
1&
b011010110 (
#2305
0&
#2310
b0110000011110111 $
b1001111100001001 %
1&
b011010111 (
#2315
0&
#2320
b0101111100000111 $
b1010000011111001 %
1&
b011011000 (
#2325
0&
#2330
b0101110100010110 $
b1010001011101010 %
1&
b011011001 (
#2335
0&
#2340
b0101101100100110 $
b1010010011011010 %
1&
b011011010 (
#2345
0&
#2350
b0101100100110101 $
b1010011011001011 %
1&
b011011011 (
#2355
0&
#2360
b0101011101000101 $
b1010100010111011 %
1&
b011011100 (
#2365
0&
#2370
b0101010101010100 $
b1010101010101100 %
1&
b011011101 (
#2375
0&
#2380
b0101001101100100 $
b1010110010011100 %
1&
b011011110 (
#2385
0&
#2390
b0101000101110011 $
b1010111010001101 %
1&
b011011111 (
#2395
0&
#2400
b0100111110000011 $
b1011000001111101 %
1&
b011100000 (
#2405
0&
#2410
b0100110110010010 $
b1011001001101110 %
1&
b011100001 (
#2415
0&
#2420
b0100101110100010 $
b1011010001011110 %
1&
b011100010 (
#2425
0&
#2430
b0100100110110001 $
b1011011001001111 %
1&
b011100011 (
#2435
0&
#2440
b0100011111000001 $
b1011100000111111 %
1&
b011100100 (
#2445
0&
#2450
b0100010111010000 $
b1011101000110000 %
1&
b011100101 (
#2455
0&
#2460
b0100001111100000 $
b1011110000100000 %
1&
b011100110 (
#2465
0&
#2470
b0100000111101111 $
b1011111000010001 %
1&
b011100111 (
#2475
0&
#2480
b0011111111111111 $
b1100000000000001 %
1&
b011101000 (
#2485
0&
#2490
b0011111000001111 $
b1100000111110001 %
1&
b011101001 (
#2495
0&
#2500
b0011110000011110 $
b1100001111100010 %
1&
b011101010 (
#2505
0&
#2510
b0011101000101110 $
b1100010111010010 %
1&
b011101011 (
#2515
0&
#2520
b0011100000111101 $
b1100011111000011 %
1&
b011101100 (
#2525
0&
#2530
b0011011001001101 $
b1100100110110011 %
1&
b011101101 (
#2535
0&
#2540
b0011010001011100 $
b1100101110100100 %
1&
b011101110 (
#2545
0&
#2550
b0011001001101100 $
b1100110110010100 %
1&
b011101111 (
#2555
0&
#2560
b0011000001111011 $
b1100111110000101 %
1&
b011110000 (
#2565
0&
#2570
b0010111010001011 $
b1101000101110101 %
1&
b011110001 (
#2575
0&
#2580
b0010110010011010 $
b1101001101100110 %
1&
b011110010 (
#2585
0&
#2590
b0010101010101010 $
b1101010101010110 %
1&
b011110011 (
#2595
0&
#2600
b0010100010111001 $
b1101011101000111 %
1&
b011110100 (
#2605
0&
#2610
b0010011011001001 $
b1101100100110111 %
1&
b011110101 (
#2615
0&
#2620
b0010010011011000 $
b1101101100101000 %
1&
b011110110 (
#2625
0&
#2630
b0010001011101000 $
b1101110100011000 %
1&
b011110111 (
#2635
0&
#2640
b0010000011110111 $
b1101111100001001 %
1&
b011111000 (
#2645
0&
#2650
b0001111100000111 $
b1110000011111001 %
1&
b011111001 (
#2655
0&
#2660
b0001110100010111 $
b1110001011101001 %
1&
b011111010 (
#2665
0&
#2670
b0001101100100110 $
b1110010011011010 %
1&
b011111011 (
#2675
0&
#2680
b0001100100110110 $
b1110011011001010 %
1&
b011111100 (
#2685
0&
#2690
b0001011101000101 $
b1110100010111011 %
1&
b011111101 (
#2695
0&
#2700
b0001010101010101 $
b1110101010101011 %
1&
b011111110 (
#2705
0&
#2710
b0001001101100100 $
b1110110010011100 %
1&
b011111111 (
#2715
0&
#2720
b0001000101110100 $
b1110111010001100 %
1&
b100000000 (
#2725
0&
#2730
b0000111110000011 $
b1111000001111101 %
1&
b100000001 (
#2735
0&
#2740
b0000110110010011 $
b1111001001101101 %
1&
b100000010 (
#2745
0&
#2750
b0000101110100010 $
b1111010001011110 %
1&
b100000011 (
#2755
0&
#2760
b0000100110110010 $
b1111011001001110 %
1&
b100000100 (
#2765
0&
#2770
b0000011111000001 $
b1111100000111111 %
1&
b100000101 (
#2775
0&
#2780
b0000010111010001 $
b1111101000101111 %
1&
b100000110 (
#2785
0&
#2790
b0000001111100000 $
b1111110000100000 %
1&
b100000111 (
#2795
0&
#2800
b0000000111110000 $
b1111111000010000 %
1&
b100001000 (
#2805
0&
#2810
b0000000000000000 $
b0000000000000000 %
1&
b100001001 (
#2815
0&
#2820
b1111111000010000 $
b0000000111110000 %
1&
b100001010 (
#2825
0&
#2830
b1111110000100000 $
b0000001111100000 %
1&
b100001011 (
#2835
0&
#2840
b1111101000101111 $
b0000010111010001 %
1&
b100001100 (
#2845
0&
#2850
b1111100000111111 $
b0000011111000001 %
1&
b100001101 (
#2855
0&
#2860
b1111011001001110 $
b0000100110110010 %
1&
b100001110 (
#2865
0&
#2870
b1111010001011110 $
b0000101110100010 %
1&
b100001111 (
#2875
0&
#2880
b1111001001101101 $
b0000110110010011 %
1&
b100010000 (
#2885
0&
#2890
b1111000001111101 $
b0000111110000011 %
1&
b100010001 (
#2895
0&
#2900
b1110111010001100 $
b0001000101110100 %
1&
b100010010 (
#2905
0&
#2910
b1110110010011100 $
b0001001101100100 %
1&
b100010011 (
#2915
0&
#2920
b1110101010101011 $
b0001010101010101 %
1&
b100010100 (
#2925
0&
#2930
b1110100010111011 $
b0001011101000101 %
1&
b100010101 (
#2935
0&
#2940
b1110011011001010 $
b0001100100110110 %
1&
b100010110 (
#2945
0&
#2950
b1110010011011010 $
b0001101100100110 %
1&
b100010111 (
#2955
0&
#2960
b1110001011101001 $
b0001110100010111 %
1&
b100011000 (
#2965
0&
#2970
b1110000011111001 $
b0001111100000111 %
1&
b100011001 (
#2975
0&
#2980
b1101111100001001 $
b0010000011110111 %
1&
b100011010 (
#2985
0&
#2990
b1101110100011000 $
b0010001011101000 %
1&
b100011011 (
#2995
0&
#3000
b1101101100101000 $
b0010010011011000 %
1&
b100011100 (
#3005
0&
#3010
b1101100100110111 $
b0010011011001001 %
1&
b100011101 (
#3015
0&
#3020
b1101011101000111 $
b0010100010111001 %
1&
b100011110 (
#3025
0&
#3030
b1101010101010110 $
b0010101010101010 %
1&
b100011111 (
#3035
0&
#3040
b1101001101100110 $
b0010110010011010 %
1&
b100100000 (
#3045
0&
#3050
b1101000101110101 $
b0010111010001011 %
1&
b100100001 (
#3055
0&
#3060
b1100111110000101 $
b0011000001111011 %
1&
b100100010 (
#3065
0&
#3070
b1100110110010100 $
b0011001001101100 %
1&
b100100011 (
#3075
0&
#3080
b1100101110100100 $
b0011010001011100 %
1&
b100100100 (
#3085
0&
#3090
b1100100110110011 $
b0011011001001101 %
1&
b100100101 (
#3095
0&
#3100
b1100011111000011 $
b0011100000111101 %
1&
b100100110 (
#3105
0&
#3110
b1100010111010010 $
b0011101000101110 %
1&
b100100111 (
#3115
0&
#3120
b1100001111100010 $
b0011110000011110 %
1&
b100101000 (
#3125
0&
#3130
b1100000111110001 $
b0011111000001111 %
1&
b100101001 (
#3135
0&
#3140
b1100000000000001 $
b0011111111111111 %
1&
b100101010 (
#3145
0&
#3150
b1011111000010001 $
b0100000111101111 %
1&
b100101011 (
#3155
0&
#3160
b1011110000100000 $
b0100001111100000 %
1&
b100101100 (
#3165
0&
#3170
b1011101000110000 $
b0100010111010000 %
1&
b100101101 (
#3175
0&
#3180
b1011100000111111 $
b0100011111000001 %
1&
b100101110 (
#3185
0&
#3190
b1011011001001111 $
b0100100110110001 %
1&
b100101111 (
#3195
0&
#3200
b1011010001011110 $
b0100101110100010 %
1&
b100110000 (
#3205
0&
#3210
b1011001001101110 $
b0100110110010010 %
1&
b100110001 (
#3215
0&
#3220
b1011000001111101 $
b0100111110000011 %
1&
b100110010 (
#3225
0&
#3230
b1010111010001101 $
b0101000101110011 %
1&
b100110011 (
#3235
0&
#3240
b1010110010011100 $
b0101001101100100 %
1&
b100110100 (
#3245
0&
#3250
b1010101010101100 $
b0101010101010100 %
1&
b100110101 (
#3255
0&
#3260
b1010100010111011 $
b0101011101000101 %
1&
b100110110 (
#3265
0&
#3270
b1010011011001011 $
b0101100100110101 %
1&
b100110111 (
#3275
0&
#3280
b1010010011011010 $
b0101101100100110 %
1&
b100111000 (
#3285
0&
#3290
b1010001011101010 $
b0101110100010110 %
1&
b100111001 (
#3295
0&
#3300
b1010000011111001 $
b0101111100000111 %
1&
b100111010 (
#3305
0&
#3310
b1001111100001001 $
b0110000011110111 %
1&
b100111011 (
#3315
0&
#3320
b1001110100011001 $
b0110001011100111 %
1&
b100111100 (
#3325
0&
#3330
b1001101100101000 $
b0110010011011000 %
1&
b100111101 (
#3335
0&
#3340
b1001100100111000 $
b0110011011001000 %
1&
b100111110 (
#3345
0&
#3350
b1001011101000111 $
b0110100010111001 %
1&
b100111111 (
#3355
0&
#3360
b1001010101010111 $
b0110101010101001 %
1&
b101000000 (
#3365
0&
#3370
b1001001101100110 $
b0110110010011010 %
1&
b101000001 (
#3375
0&
#3380
b1001000101110110 $
b0110111010001010 %
1&
b101000010 (
#3385
0&
#3390
b1000111110000101 $
b0111000001111011 %
1&
b101000011 (
#3395
0&
#3400
b1000110110010101 $
b0111001001101011 %
1&
b101000100 (
#3405
0&
#3410
b1000101110100100 $
b0111010001011100 %
1&
b101000101 (
#3415
0&
#3420
b1000100110110100 $
b0111011001001100 %
1&
b101000110 (
#3425
0&
#3430
b1000011111000011 $
b0111100000111101 %
1&
b101000111 (
#3435
0&
#3440
b1000010111010011 $
b0111101000101101 %
1&
b101001000 (
#3445
0&
#3450
b1000001111100010 $
b0111110000011110 %
1&
b101001001 (
#3455
0&
#3460
b1000000111110010 $
b0111111000001110 %
1&
b101001010 (
#3465
0&
#3470
b1000000000000001 $
b0111111111111111 %
1&
b101001011 (
#3475
0&
#3480
b1000010111010011 #
1&
b101001100 (
#3485
0&
#3490
b1000101110100100 #
1&
b101001101 (
#3495
0&
#3500
b1001000101110110 #
1&
b101001110 (
#3505
0&
#3510
b1001011101000111 #
1&
b101001111 (
#3515
0&
#3520
b1001110100011001 #
1&
b101010000 (
#3525
0&
#3530
b1010001011101010 #
1&
b101010001 (
#3535
0&
#3540
b1010100010111011 #
1&
b101010010 (
#3545
0&
#3550
b1010111010001101 #
1&
b101010011 (
#3555
0&
#3560
b1011010001011110 #
1&
b101010100 (
#3565
0&
#3570
b1011101000110000 #
1&
b101010101 (
#3575
0&
#3580
b1100000000000001 #
1&
b101010110 (
#3585
0&
#3590
b1100010111010010 #
1&
b101010111 (
#3595
0&
#3600
b1100101110100100 #
1&
b101011000 (
#3605
0&
#3610
b1101000101110101 #
1&
b101011001 (
#3615
0&
#3620
b1101011101000111 #
1&
b101011010 (
#3625
0&
#3630
b1101110100011000 #
1&
b101011011 (
#3635
0&
#3640
b1110001011101001 #
1&
b101011100 (
